djangorestframework_ext-0.29.dist-info/licenses/LICENSE
rest_framework_ext/__init__.py
rest_framework_ext/mixins.py
rest_framework_ext/pagination.py
rest_framework_ext/permissions.py
rest_framework_ext/serializers.py
rest_framework_ext/settings.py
rest_framework_ext/utils.py
rest_framework_ext/validators.py
rest_framework_ext/views.py
djangorestframework_ext-0.29.dist-info/METADATA
djangorestframework_ext-0.29.dist-info/WHEEL
djangorestframework_ext-0.29.dist-info/top_level.txt
djangorestframework_ext-0.29.dist-info/RECORD
